rivertrace/__init__.py
rivertrace/functions.py
rivertrace/main.py
rivertrace-1.1.1.dist-info/LICENSE
rivertrace-1.1.1.dist-info/METADATA
rivertrace-1.1.1.dist-info/WHEEL
rivertrace-1.1.1.dist-info/top_level.txt
rivertrace-1.1.1.dist-info/RECORD
