Metadata-Version: 2.1
Name: rivertrace
Version: 1.1.1
Summary: Identifies rivers in satellite images and generates a path of pixel values along its length.
Home-page: https://github.com/JamesRunnalls/river-trace
Author: James Runnalls
Author-email: runnalls.james@gmail.com
License: GNU GENERAL PUBLIC LICENSE
Platform: UNKNOWN
License-File: LICENSE
Requires-Dist: numpy
Requires-Dist: scikit-image
Requires-Dist: networkx (==2.3.0)
